Adv2/Adv.py
Adv2/Adv2File.py
Adv2/AdvError.py
Adv2/AdvLib.py
Adv2/UnitTestSample.adv
Adv2/Version.py
Adv2/__init__.py
Adv2/Adv2DLLlibs/AdvLib.Core32.dll
Adv2/Adv2DLLlibs/AdvLib.Core64.dll
Adv2/Adv2DLLlibs/libAdvCore.dylib
Adv2/Adv2DLLlibs/libAdvCore32.so
Adv2/Adv2DLLlibs/libAdvCore64.so
Adv2-1.2.0.dist-info/METADATA
Adv2-1.2.0.dist-info/WHEEL
Adv2-1.2.0.dist-info/top_level.txt
Adv2-1.2.0.dist-info/RECORD
