Metadata-Version: 2.1
Name: Adv2
Version: 1.2.0
Summary: Adv2reader reads version 2 Astro Digital Video files.
Home-page: https://github.com/bob-anderson-ok/adv2reader
Author: Bob Anderson
Author-email: bob.anderson.ok@gmail.com
Maintainer: Bob Anderson
Maintainer-email: bob.anderson.ok@gmail.com
License: License :: OSI Approved :: MIT License
Keywords: ADV file reader,Astro Digital Video version 2 file reader
Platform: UNKNOWN
Classifier: Development Status :: 5 - Production/Stable
Classifier: Intended Audience :: Science/Research
Classifier: Natural Language :: English
Classifier: License :: OSI Approved :: MIT License
Classifier: Operating System :: MacOS :: MacOS X
Classifier: Operating System :: Microsoft :: Windows
Classifier: Operating System :: POSIX :: Linux
Classifier: Programming Language :: Python :: 3.7
Classifier: Topic :: Scientific/Engineering
Requires-Python: >=3.7
